distil/__init__.py
distil/utils.py
distil/version.py
distil/modeling/__init__.py
distil/modeling/base.py
distil/modeling/bert_models.py
distil/modeling/clustering.py
distil/modeling/collaborative_filtering.py
distil/modeling/community_detection.py
distil/modeling/failure_model.py
distil/modeling/fixed_cnn.py
distil/modeling/forest.py
distil/modeling/helpers.py
distil/modeling/link_prediction.py
distil/modeling/metrics.py
distil/modeling/neighbors.py
distil/modeling/pretrained_audio.py
distil/modeling/sgm.py
distil/modeling/svm.py
distil/modeling/text_classification.py
distil/modeling/vertex_nomination.py
distil/preprocessing/__init__.py
distil/preprocessing/transformers.py
distil/primitives/__init__.py
distil/primitives/audio_reader.py
distil/primitives/audio_transfer.py
distil/primitives/bert_classifier.py
distil/primitives/binary_encoder.py
distil/primitives/categorical_imputer.py
distil/primitives/collaborative_filtering_link_prediction.py
distil/primitives/column_parser.py
distil/primitives/community_detection.py
distil/primitives/enrich_dates.py
distil/primitives/ensemble_forest.py
distil/primitives/image_transfer.py
distil/primitives/k_means.py
distil/primitives/link_prediction.py
distil/primitives/list_to_dataframe.py
distil/primitives/load_edgelist.py
distil/primitives/load_graphs.py
distil/primitives/load_single_graph.py
distil/primitives/one_hot_encoder.py
distil/primitives/ranked_linear_svc.py
distil/primitives/replace_singletons.py
distil/primitives/satellite_image_loader.py
distil/primitives/seeded_graph_matching.py
distil/primitives/text_classifier.py
distil/primitives/text_encoder.py
distil/primitives/time_series_formatter.py
distil/primitives/utils.py
distil/primitives/vertex_nomination.py
distil/third_party/__init__.py
distil/third_party/audioset/__init__.py
distil/third_party/audioset/mel_features.py
distil/third_party/audioset/vggish_inference_demo.py
distil/third_party/audioset/vggish_input.py
distil/third_party/audioset/vggish_params.py
distil_primitives-0.8.3.dist-info/LICENSE.txt
distil_primitives-0.8.3.dist-info/METADATA
distil_primitives-0.8.3.dist-info/NOTICE.md
distil_primitives-0.8.3.dist-info/WHEEL
distil_primitives-0.8.3.dist-info/entry_points.txt
distil_primitives-0.8.3.dist-info/top_level.txt
distil_primitives-0.8.3.dist-info/RECORD
