Metadata-Version: 2.1
Name: distil-primitives
Version: 0.8.3
Summary: Distil primitives as a single library
Home-page: UNKNOWN
License: Apache-2.0
Keywords: d3m_primitive
Platform: UNKNOWN
Requires-Dist: basenet
Requires-Dist: d3m
Requires-Dist: fastdtw (>=0.3.2)
Requires-Dist: frozendict (>=1.2)
Requires-Dist: joblib (>=0.13.2)
Requires-Dist: networkx (==2.4)
Requires-Dist: nonneg-rescal (<0.2,>=0.1)
Requires-Dist: numpy
Requires-Dist: pandas (>=1.1.3)
Requires-Dist: pillow (==7.1.2)
Requires-Dist: pyprctl (<0.2,>=0.1)
Requires-Dist: pytorch-pretrained-bert (==0.4.0)
Requires-Dist: resampy (>=0.2.1)
Requires-Dist: rescal (==0.4)
Requires-Dist: scikit-image (<=0.17.2)
Requires-Dist: scikit-learn (==0.22.2.post1)
Requires-Dist: scipy (==1.4.1)
Requires-Dist: seeded-graph-matching (<1.1,>=1.0.3)
Requires-Dist: shap (>=0.29)
Requires-Dist: sklearn-pandas (==1.8.0)
Requires-Dist: soundfile (>=0.10.2)
Requires-Dist: torch (>=1.4.0)
Requires-Dist: torchvggish (<0.3,>=0.2)
Requires-Dist: torchvision (>=0.5.0)
Provides-Extra: cpu
Requires-Dist: tensorflow (==2.2.0) ; extra == 'cpu'
Provides-Extra: gpu
Requires-Dist: tensorflow-gpu (==2.2.0) ; extra == 'gpu'
